{"author":{"name":null,"type":"card","url":"https://ohmycloud.github.io/"},"content":{"html":"\u003ch1 id=\"斐波那契数列fibonacci-sequence\"\u003e斐波那契数列(Fibonacci sequence)\u003c/h1\u003e\n\u003cdiv class=\"highlight\"\u003e\u003cpre tabindex=\"0\" class=\"chroma\"\u003e\u003ccode class=\"language-perl6\" data-lang=\"perl6\"\u003e\u003cspan class=\"line\"\u003e\u003cspan class=\"cl\"\u003e\u003cspan class=\"nb\"\u003elazy\u003c/span\u003e \u003cspan class=\"k\"\u003emy\u003c/span\u003e \u003cspan class=\"nv\"\u003e\\sequence\u003c/span\u003e \u003cspan class=\"o\"\u003e=\u003c/span\u003e \u003cspan class=\"mi\"\u003e1\u003c/span\u003e\u003cspan class=\"o\"\u003e,\u003c/span\u003e \u003cspan class=\"mi\"\u003e1\u003c/span\u003e\u003cspan class=\"o\"\u003e,\u003c/span\u003e \u003cspan class=\"p\"\u003e{\u003c/span\u003e\u003cspan class=\"nv\"\u003e$^a\u003c/span\u003e \u003cspan class=\"o\"\u003e+\u003c/span\u003e \u003cspan class=\"nv\"\u003e$^b\u003c/span\u003e \u003cspan class=\"p\"\u003e}\u003c/span\u003e \u003cspan class=\"o\"\u003e...\u003c/span\u003e \u003cspan class=\"o\"\u003e*\u003c/span\u003e\u003cspan class=\"p\"\u003e;\u003c/span\u003e\n\u003c/span\u003e\u003c/span\u003e\u003cspan class=\"line\"\u003e\u003cspan class=\"cl\"\u003e\u003cspan class=\"nb\"\u003esay\u003c/span\u003e \u003cspan class=\"n\"\u003esequence\u003c/span\u003e\u003cspan class=\"o\"\u003e.\u003c/span\u003e\u003cspan class=\"nb\"\u003eraku\u003c/span\u003e\u003cspan class=\"p\"\u003e;\u003c/span\u003e        \u003cspan class=\"c1\"\u003e# 1, 1, 2, 3, 5...\u003c/span\u003e\n\u003c/span\u003e\u003c/span\u003e\u003cspan class=\"line\"\u003e\u003cspan class=\"cl\"\u003e\u003cspan class=\"nb\"\u003esay\u003c/span\u003e \u003cspan class=\"o\"\u003e[+]\u003c/span\u003e \u003cspan class=\"n\"\u003esequence\u003c/span\u003e\u003cspan class=\"o\"\u003e[\u003c/span\u003e\u003cspan class=\"mi\"\u003e0\u003c/span\u003e\u003cspan class=\"o\"\u003e..^\u003c/span\u003e\u003cspan class=\"mi\"\u003e10\u003c/span\u003e\u003cspan class=\"o\"\u003e]\u003c/span\u003e\u003cspan class=\"p\"\u003e;\u003c/span\u003e \u003cspan class=\"c1\"\u003e# 143\u003c/span\u003e\n\u003c/span\u003e\u003c/span\u003e\u003c/code\u003e\u003c/pre\u003e\u003c/div\u003e\u003ch1 id=\"等差数列arithmetic-sequence\"\u003e等差数列(arithmetic sequence)\u003c/h1\u003e\n\u003ch2 id=\"通项为-n\"\u003e通项为 n\u003c/h2\u003e\n\u003cdiv class=\"highlight\"\u003e\u003cpre tabindex=\"0\" class=\"chroma\"\u003e\u003ccode class=\"language-perl6\" data-lang=\"perl6\"\u003e\u003cspan class=\"line\"\u003e\u003cspan class=\"cl\"\u003e\u003cspan class=\"nb\"\u003elazy\u003c/span\u003e \u003cspan class=\"k\"\u003emy\u003c/span\u003e \u003cspan class=\"nv\"\u003e\\sequence\u003c/span\u003e \u003cspan class=\"o\"\u003e=\u003c/span\u003e \u003cspan class=\"mi\"\u003e1\u003c/span\u003e\u003cspan class=\"o\"\u003e,\u003c/span\u003e \u003cspan class=\"mi\"\u003e2\u003c/span\u003e\u003cspan class=\"o\"\u003e,\u003c/span\u003e \u003cspan class=\"mi\"\u003e3\u003c/span\u003e \u003cspan class=\"o\"\u003e...\u003c/span\u003e \u003cspan class=\"o\"\u003e*\u003c/span\u003e\u003cspan class=\"p\"\u003e;\u003c/span\u003e\n\u003c/span\u003e\u003c/span\u003e\u003cspan class=\"line\"\u003e\u003cspan class=\"cl\"\u003e\u003cspan class=\"nb\"\u003esay\u003c/span\u003e \u003cspan class=\"n\"\u003esequence\u003c/span\u003e\u003cspan class=\"o\"\u003e.\u003c/span\u003e\u003cspan class=\"nb\"\u003eraku\u003c/span\u003e\u003cspan class=\"p\"\u003e;\u003c/span\u003e        \u003cspan class=\"c1\"\u003e# 1, 2, 3, 4, 5...\u003c/span\u003e\n\u003c/span\u003e\u003c/span\u003e\u003cspan class=\"line\"\u003e\u003cspan class=\"cl\"\u003e\u003cspan class=\"nb\"\u003esay\u003c/span\u003e \u003cspan class=\"o\"\u003e[+]\u003c/span\u003e \u003cspan class=\"n\"\u003esequence\u003c/span\u003e\u003cspan class=\"o\"\u003e[\u003c/span\u003e\u003cspan class=\"mi\"\u003e0\u003c/span\u003e\u003cspan class=\"o\"\u003e..^\u003c/span\u003e\u003cspan class=\"mi\"\u003e10\u003c/span\u003e\u003cspan class=\"o\"\u003e]\u003c/span\u003e\u003cspan class=\"p\"\u003e;\u003c/span\u003e \u003cspan class=\"c1\"\u003e# 55\u003c/span\u003e\n\u003c/span\u003e\u003c/span\u003e\u003c/code\u003e\u003c/pre\u003e\u003c/div\u003e\u003ch2 id=\"通项为-2n\"\u003e通项为 2n\u003c/h2\u003e\n\u003cdiv class=\"highlight\"\u003e\u003cpre tabindex=\"0\" class=\"chroma\"\u003e\u003ccode class=\"language-perl6\" data-lang=\"perl6\"\u003e\u003cspan class=\"line\"\u003e\u003cspan class=\"cl\"\u003e\u003cspan class=\"nb\"\u003elazy\u003c/span\u003e \u003cspan class=\"k\"\u003emy\u003c/span\u003e \u003cspan class=\"nv\"\u003e\\sequence\u003c/span\u003e \u003cspan class=\"o\"\u003e=\u003c/span\u003e \u003cspan class=\"mi\"\u003e2\u003c/span\u003e\u003cspan class=\"o\"\u003e,\u003c/span\u003e \u003cspan class=\"mi\"\u003e4\u003c/span\u003e\u003cspan class=\"o\"\u003e,\u003c/span\u003e \u003cspan class=\"mi\"\u003e6\u003c/span\u003e \u003cspan class=\"o\"\u003e...\u003c/span\u003e \u003cspan class=\"o\"\u003e*\u003c/span\u003e\u003cspan class=\"p\"\u003e;\u003c/span\u003e\n\u003c/span\u003e\u003c/span\u003e\u003cspan class=\"line\"\u003e\u003cspan class=\"cl\"\u003e\u003cspan class=\"nb\"\u003esay\u003c/span\u003e \u003cspan class=\"n\"\u003esequence\u003c/span\u003e\u003cspan class=\"o\"\u003e.\u003c/span\u003e\u003cspan class=\"nb\"\u003eraku\u003c/span\u003e\u003cspan class=\"p\"\u003e;\u003c/span\u003e        \u003cspan class=\"c1\"\u003e# 2, 4, 6, 8, 10\u003c/span\u003e\n\u003c/span\u003e\u003c/span\u003e\u003cspan class=\"line\"\u003e\u003cspan class=\"cl\"\u003e\u003cspan class=\"nb\"\u003esay\u003c/span\u003e \u003cspan class=\"o\"\u003e[+]\u003c/span\u003e \u003cspan class=\"n\"\u003esequence\u003c/span\u003e\u003cspan class=\"o\"\u003e[\u003c/span\u003e\u003cspan class=\"mi\"\u003e0\u003c/span\u003e\u003cspan class=\"o\"\u003e..^\u003c/span\u003e\u003cspan class=\"mi\"\u003e10\u003c/span\u003e\u003cspan class=\"o\"\u003e]\u003c/span\u003e\u003cspan class=\"p\"\u003e;\u003c/span\u003e \u003cspan class=\"c1\"\u003e# 110\u003c/span\u003e\n\u003c/span\u003e\u003c/span\u003e\u003c/code\u003e\u003c/pre\u003e\u003c/div\u003e\u003ch2 id=\"通项为-2n---1\"\u003e通项为 2n - 1\u003c/h2\u003e\n\u003cdiv class=\"highlight\"\u003e\u003cpre tabindex=\"0\" class=\"chroma\"\u003e\u003ccode class=\"language-perl6\" data-lang=\"perl6\"\u003e\u003cspan class=\"line\"\u003e\u003cspan class=\"cl\"\u003e\u003cspan class=\"nb\"\u003elazy\u003c/span\u003e \u003cspan class=\"k\"\u003emy\u003c/span\u003e \u003cspan class=\"nv\"\u003e\\sequence\u003c/span\u003e \u003cspan class=\"o\"\u003e=\u003c/span\u003e \u003cspan class=\"mi\"\u003e1\u003c/span\u003e\u003cspan class=\"o\"\u003e,\u003c/span\u003e \u003cspan class=\"mi\"\u003e3\u003c/span\u003e\u003cspan class=\"o\"\u003e,\u003c/span\u003e \u003cspan class=\"mi\"\u003e5\u003c/span\u003e \u003cspan class=\"o\"\u003e...\u003c/span\u003e \u003cspan class=\"o\"\u003e*\u003c/span\u003e\u003cspan class=\"p\"\u003e;\u003c/span\u003e\n\u003c/span\u003e\u003c/span\u003e\u003cspan class=\"line\"\u003e\u003cspan class=\"cl\"\u003e\u003cspan class=\"nb\"\u003esay\u003c/span\u003e \u003cspan class=\"n\"\u003esequence\u003c/span\u003e\u003cspan class=\"o\"\u003e.\u003c/span\u003e\u003cspan class=\"nb\"\u003eraku\u003c/span\u003e\u003cspan class=\"p\"\u003e;\u003c/span\u003e        \u003cspan class=\"c1\"\u003e# 1, 3, 5, 7, 9...\u003c/span\u003e\n\u003c/span\u003e\u003c/span\u003e\u003cspan class=\"line\"\u003e\u003cspan class=\"cl\"\u003e\u003cspan class=\"nb\"\u003esay\u003c/span\u003e \u003cspan class=\"o\"\u003e[+]\u003c/span\u003e \u003cspan class=\"n\"\u003esequence\u003c/span\u003e\u003cspan class=\"o\"\u003e[\u003c/span\u003e\u003cspan class=\"mi\"\u003e0\u003c/span\u003e\u003cspan class=\"o\"\u003e..^\u003c/span\u003e\u003cspan class=\"mi\"\u003e10\u003c/span\u003e\u003cspan class=\"o\"\u003e]\u003c/span\u003e\u003cspan class=\"p\"\u003e;\u003c/span\u003e \u003cspan class=\"c1\"\u003e# 100\u003c/span\u003e\n\u003c/span\u003e\u003c/span\u003e\u003c/code\u003e\u003c/pre\u003e\u003c/div\u003e\u003ch1 id=\"等比数列\"\u003e等比数列\u003c/h1\u003e\n\u003ch2 id=\"通项为-2ⁿ\"\u003e通项为 2ⁿ⁻¹\u003c/h2\u003e\n\u003cdiv class=\"highlight\"\u003e\u003cpre tabindex=\"0\" class=\"chroma\"\u003e\u003ccode class=\"language-perl6\" data-lang=\"perl6\"\u003e\u003cspan class=\"line\"\u003e\u003cspan class=\"cl\"\u003e\u003cspan class=\"k\"\u003emy\u003c/span\u003e \u003cspan class=\"nv\"\u003e\\sequence\u003c/span\u003e \u003cspan class=\"o\"\u003e:=\u003c/span\u003e \u003cspan class=\"mi\"\u003e1\u003c/span\u003e\u003cspan class=\"o\"\u003e,\u003c/span\u003e \u003cspan class=\"mi\"\u003e2\u003c/span\u003e\u003cspan class=\"o\"\u003e,\u003c/span\u003e \u003cspan class=\"mi\"\u003e4\u003c/span\u003e \u003cspan class=\"o\"\u003e...\u003c/span\u003e \u003cspan class=\"o\"\u003e*\u003c/span\u003e\u003cspan class=\"p\"\u003e;\u003c/span\u003e\n\u003c/span\u003e\u003c/span\u003e\u003cspan class=\"line\"\u003e\u003cspan class=\"cl\"\u003e\u003cspan class=\"nb\"\u003esay\u003c/span\u003e \u003cspan class=\"n\"\u003esequence\u003c/span\u003e\u003cspan class=\"o\"\u003e.\u003c/span\u003e\u003cspan class=\"nb\"\u003eraku\u003c/span\u003e\u003cspan class=\"p\"\u003e;\u003c/span\u003e        \u003cspan class=\"c1\"\u003e# 1, 2, 4, 8, 16...\u003c/span\u003e\n\u003c/span\u003e\u003c/span\u003e\u003cspan class=\"line\"\u003e\u003cspan class=\"cl\"\u003e\u003cspan class=\"nb\"\u003esay\u003c/span\u003e \u003cspan class=\"o\"\u003e[+]\u003c/span\u003e \u003cspan class=\"n\"\u003esequence\u003c/span\u003e\u003cspan class=\"o\"\u003e[\u003c/span\u003e\u003cspan class=\"mi\"\u003e0\u003c/span\u003e\u003cspan class=\"o\"\u003e..^\u003c/span\u003e\u003cspan class=\"mi\"\u003e10\u003c/span\u003e\u003cspan class=\"o\"\u003e]\u003c/span\u003e\u003cspan class=\"p\"\u003e;\u003c/span\u003e \u003cspan class=\"c1\"\u003e# 1023\u003c/span\u003e\n\u003c/span\u003e\u003c/span\u003e\u003c/code\u003e\u003c/pre\u003e\u003c/div\u003e\u003cp\u003e或:\u003c/p\u003e\n\u003cdiv class=\"highlight\"\u003e\u003cpre tabindex=\"0\" class=\"chroma\"\u003e\u003ccode class=\"language-perl6\" data-lang=\"perl6\"\u003e\u003cspan class=\"line\"\u003e\u003cspan class=\"cl\"\u003e\u003cspan class=\"k\"\u003emy\u003c/span\u003e \u003cspan class=\"nv\"\u003e\\sequence\u003c/span\u003e \u003cspan class=\"o\"\u003e:=\u003c/span\u003e \u003cspan class=\"p\"\u003e{\u003c/span\u003e \u003cspan class=\"k\"\u003estate\u003c/span\u003e \u003cspan class=\"nv\"\u003e$n\u003c/span\u003e \u003cspan class=\"o\"\u003e=\u003c/span\u003e \u003cspan class=\"mi\"\u003e1\u003c/span\u003e\u003cspan class=\"p\"\u003e;\u003c/span\u003e \u003cspan class=\"mi\"\u003e2\u003c/span\u003e \u003cspan class=\"o\"\u003e**\u003c/span\u003e \u003cspan class=\"p\"\u003e(\u003c/span\u003e\u003cspan class=\"nv\"\u003e$n\u003c/span\u003e\u003cspan class=\"o\"\u003e++\u003c/span\u003e \u003cspan class=\"o\"\u003e-\u003c/span\u003e\u003cspan class=\"mi\"\u003e1\u003c/span\u003e\u003cspan class=\"p\"\u003e)\u003c/span\u003e \u003cspan class=\"p\"\u003e}\u003c/span\u003e \u003cspan class=\"o\"\u003e...\u003c/span\u003e \u003cspan class=\"o\"\u003e*\u003c/span\u003e\u003cspan class=\"p\"\u003e;\u003c/span\u003e\n\u003c/span\u003e\u003c/span\u003e\u003cspan class=\"line\"\u003e\u003cspan class=\"cl\"\u003e\u003cspan class=\"nb\"\u003esay\u003c/span\u003e \u003cspan class=\"n\"\u003esequence\u003c/span\u003e\u003cspan class=\"o\"\u003e.\u003c/span\u003e\u003cspan class=\"nb\"\u003eraku\u003c/span\u003e\u003cspan class=\"p\"\u003e;\u003c/span\u003e        \u003cspan class=\"c1\"\u003e# 1, 2, 4, 8, 16...\u003c/span\u003e\n\u003c/span\u003e\u003c/span\u003e\u003cspan class=\"line\"\u003e\u003cspan class=\"cl\"\u003e\u003cspan class=\"nb\"\u003esay\u003c/span\u003e \u003cspan class=\"o\"\u003e[+]\u003c/span\u003e \u003cspan class=\"n\"\u003esequence\u003c/span\u003e\u003cspan class=\"o\"\u003e[\u003c/span\u003e\u003cspan class=\"mi\"\u003e0\u003c/span\u003e\u003cspan class=\"o\"\u003e..^\u003c/span\u003e\u003cspan class=\"mi\"\u003e10\u003c/span\u003e\u003cspan class=\"o\"\u003e]\u003c/span\u003e\u003cspan class=\"p\"\u003e;\u003c/span\u003e \u003cspan class=\"c1\"\u003e# 1023\u003c/span\u003e\n\u003c/span\u003e\u003c/span\u003e\u003c/code\u003e\u003c/pre\u003e\u003c/div\u003e\u003ch2 id=\"通项为--1ⁿ\"\u003e通项为 -1ⁿ\u003c/h2\u003e\n\u003cdiv class=\"highlight\"\u003e\u003cpre tabindex=\"0\" class=\"chroma\"\u003e\u003ccode class=\"language-perl6\" data-lang=\"perl6\"\u003e\u003cspan class=\"line\"\u003e\u003cspan class=\"cl\"\u003e\u003cspan class=\"nb\"\u003elazy\u003c/span\u003e \u003cspan class=\"k\"\u003emy\u003c/span\u003e \u003cspan class=\"nv\"\u003e\\sequence\u003c/span\u003e \u003cspan class=\"o\"\u003e=\u003c/span\u003e \u003cspan class=\"o\"\u003e-\u003c/span\u003e\u003cspan class=\"mi\"\u003e1\u003c/span\u003e\u003cspan class=\"o\"\u003e,\u003c/span\u003e\u003cspan class=\"mi\"\u003e1\u003c/span\u003e\u003cspan class=\"o\"\u003e,-\u003c/span\u003e\u003cspan class=\"mi\"\u003e1\u003c/span\u003e \u003cspan class=\"o\"\u003e...\u003c/span\u003e \u003cspan class=\"o\"\u003e*\u003c/span\u003e\u003cspan class=\"p\"\u003e;\u003c/span\u003e\n\u003c/span\u003e\u003c/span\u003e\u003cspan class=\"line\"\u003e\u003cspan class=\"cl\"\u003e\u003cspan class=\"nb\"\u003esay\u003c/span\u003e \u003cspan class=\"n\"\u003esequence\u003c/span\u003e\u003cspan class=\"o\"\u003e.\u003c/span\u003e\u003cspan class=\"nb\"\u003eraku\u003c/span\u003e\u003cspan class=\"p\"\u003e;\u003c/span\u003e        \u003cspan class=\"c1\"\u003e# -1, 1, -1, 1, -1...\u003c/span\u003e\n\u003c/span\u003e\u003c/span\u003e\u003cspan class=\"line\"\u003e\u003cspan class=\"cl\"\u003e\u003cspan class=\"nb\"\u003esay\u003c/span\u003e \u003cspan class=\"o\"\u003e[+]\u003c/span\u003e \u003cspan class=\"n\"\u003esequence\u003c/span\u003e\u003cspan class=\"o\"\u003e[\u003c/span\u003e\u003cspan class=\"mi\"\u003e0\u003c/span\u003e\u003cspan class=\"o\"\u003e..^\u003c/span\u003e\u003cspan class=\"mi\"\u003e10\u003c/span\u003e\u003cspan class=\"o\"\u003e]\u003c/span\u003e\u003cspan class=\"p\"\u003e;\u003c/span\u003e \u003cspan class=\"c1\"\u003e# 0\u003c/span\u003e\n\u003c/span\u003e\u003c/span\u003e\u003c/code\u003e\u003c/pre\u003e\u003c/div\u003e\u003ch2 id=\"通项为--1ⁿ-1\"\u003e通项为 -1ⁿ⁺¹\u003c/h2\u003e\n\u003cdiv class=\"highlight\"\u003e\u003cpre tabindex=\"0\" class=\"chroma\"\u003e\u003ccode class=\"language-perl6\" data-lang=\"perl6\"\u003e\u003cspan class=\"line\"\u003e\u003cspan class=\"cl\"\u003e\u003cspan class=\"nb\"\u003elazy\u003c/span\u003e \u003cspan class=\"k\"\u003emy\u003c/span\u003e \u003cspan class=\"nv\"\u003e\\sequence\u003c/span\u003e \u003cspan class=\"o\"\u003e=\u003c/span\u003e \u003cspan class=\"mi\"\u003e1\u003c/span\u003e\u003cspan class=\"o\"\u003e,-\u003c/span\u003e\u003cspan class=\"mi\"\u003e1\u003c/span\u003e\u003cspan class=\"o\"\u003e,\u003c/span\u003e\u003cspan class=\"mi\"\u003e1\u003c/span\u003e \u003cspan class=\"o\"\u003e...\u003c/span\u003e \u003cspan class=\"o\"\u003e*\u003c/span\u003e\u003cspan class=\"p\"\u003e;\u003c/span\u003e\n\u003c/span\u003e\u003c/span\u003e\u003cspan class=\"line\"\u003e\u003cspan class=\"cl\"\u003e\u003cspan class=\"nb\"\u003esay\u003c/span\u003e \u003cspan class=\"n\"\u003esequence\u003c/span\u003e\u003cspan class=\"o\"\u003e.\u003c/span\u003e\u003cspan class=\"nb\"\u003eraku\u003c/span\u003e\u003cspan class=\"p\"\u003e;\u003c/span\u003e        \u003cspan class=\"c1\"\u003e# 1, -1, 1, -1, 1...\u003c/span\u003e\n\u003c/span\u003e\u003c/span\u003e\u003cspan class=\"line\"\u003e\u003cspan class=\"cl\"\u003e\u003cspan class=\"nb\"\u003esay\u003c/span\u003e \u003cspan class=\"o\"\u003e[+]\u003c/span\u003e \u003cspan class=\"n\"\u003esequence\u003c/span\u003e\u003cspan class=\"o\"\u003e[\u003c/span\u003e\u003cspan class=\"mi\"\u003e0\u003c/span\u003e\u003cspan class=\"o\"\u003e..^\u003c/span\u003e\u003cspan class=\"mi\"\u003e10\u003c/span\u003e\u003cspan class=\"o\"\u003e]\u003c/span\u003e\u003cspan class=\"p\"\u003e;\u003c/span\u003e \u003cspan class=\"c1\"\u003e# 0\u003c/span\u003e\n\u003c/span\u003e\u003c/span\u003e\u003c/code\u003e\u003c/pre\u003e\u003c/div\u003e\u003ch1 id=\"指数数列\"\u003e指数数列\u003c/h1\u003e\n\u003ch2 id=\"通项为-10ⁿ---1\"\u003e通项为 10ⁿ - 1\u003c/h2\u003e\n\u003cdiv class=\"highlight\"\u003e\u003cpre tabindex=\"0\" class=\"chroma\"\u003e\u003ccode class=\"language-perl6\" data-lang=\"perl6\"\u003e\u003cspan class=\"line\"\u003e\u003cspan class=\"cl\"\u003e\u003cspan class=\"k\"\u003emy\u003c/span\u003e \u003cspan class=\"nv\"\u003e\\sequence\u003c/span\u003e \u003cspan class=\"o\"\u003e:=\u003c/span\u003e \u003cspan class=\"mi\"\u003e9\u003c/span\u003e\u003cspan class=\"o\"\u003e,\u003c/span\u003e \u003cspan class=\"mi\"\u003e99\u003c/span\u003e\u003cspan class=\"o\"\u003e,\u003c/span\u003e \u003cspan class=\"k\"\u003e-\u0026gt;\u003c/span\u003e \u003cspan class=\"nv\"\u003e$a\u003c/span\u003e \u003cspan class=\"p\"\u003e{\u003c/span\u003e \u003cspan class=\"p\"\u003e(\u003c/span\u003e\u003cspan class=\"nv\"\u003e$a\u003c/span\u003e \u003cspan class=\"o\"\u003e~\u003c/span\u003e \u003cspan class=\"p\"\u003e\u0026#39;\u003c/span\u003e\u003cspan class=\"s1\"\u003e9\u003c/span\u003e\u003cspan class=\"p\"\u003e\u0026#39;)\u003c/span\u003e\u003cspan class=\"o\"\u003e.\u003c/span\u003e\u003cspan class=\"kt\"\u003eInt\u003c/span\u003e \u003cspan class=\"p\"\u003e}\u003c/span\u003e \u003cspan class=\"o\"\u003e...\u003c/span\u003e \u003cspan class=\"o\"\u003e*\u003c/span\u003e\u003cspan class=\"p\"\u003e;\u003c/span\u003e\n\u003c/span\u003e\u003c/span\u003e\u003cspan class=\"line\"\u003e\u003cspan class=\"cl\"\u003e\u003cspan class=\"nb\"\u003esay\u003c/span\u003e \u003cspan class=\"nv\"\u003e$sequence\u003c/span\u003e\u003cspan class=\"o\"\u003e.\u003c/span\u003e\u003cspan class=\"nb\"\u003eraku\u003c/span\u003e\u003cspan class=\"p\"\u003e;\u003c/span\u003e       \u003cspan class=\"c1\"\u003e# 9, 99, 999, 9999, 99999...\u003c/span\u003e\n\u003c/span\u003e\u003c/span\u003e\u003cspan class=\"line\"\u003e\u003cspan class=\"cl\"\u003e\u003cspan class=\"nb\"\u003esay\u003c/span\u003e \u003cspan class=\"o\"\u003e[+]\u003c/span\u003e \u003cspan class=\"n\"\u003esequence\u003c/span\u003e\u003cspan class=\"o\"\u003e[\u003c/span\u003e\u003cspan class=\"mi\"\u003e0\u003c/span\u003e\u003cspan class=\"o\"\u003e..^\u003c/span\u003e\u003cspan class=\"mi\"\u003e10\u003c/span\u003e\u003cspan class=\"o\"\u003e]\u003c/span\u003e\u003cspan class=\"p\"\u003e;\u003c/span\u003e \u003cspan class=\"c1\"\u003e# 11111111100\u003c/span\u003e\n\u003c/span\u003e\u003c/span\u003e\u003c/code\u003e\u003c/pre\u003e\u003c/div\u003e\u003cp\u003e或:\u003c/p\u003e\n\u003cdiv class=\"highlight\"\u003e\u003cpre tabindex=\"0\" class=\"chroma\"\u003e\u003ccode class=\"language-perl6\" data-lang=\"perl6\"\u003e\u003cspan class=\"line\"\u003e\u003cspan class=\"cl\"\u003e\u003cspan class=\"k\"\u003emy\u003c/span\u003e \u003cspan class=\"nv\"\u003e\\sequence\u003c/span\u003e \u003cspan class=\"o\"\u003e:=\u003c/span\u003e \u003cspan class=\"p\"\u003e{\u003c/span\u003e\u003cspan class=\"k\"\u003estate\u003c/span\u003e \u003cspan class=\"nv\"\u003e$n\u003c/span\u003e \u003cspan class=\"o\"\u003e=\u003c/span\u003e \u003cspan class=\"mi\"\u003e1\u003c/span\u003e\u003cspan class=\"p\"\u003e;\u003c/span\u003e \u003cspan class=\"p\"\u003e(\u003c/span\u003e\u003cspan class=\"mi\"\u003e10\u003c/span\u003e \u003cspan class=\"o\"\u003e**\u003c/span\u003e \u003cspan class=\"nv\"\u003e$n\u003c/span\u003e\u003cspan class=\"o\"\u003e++\u003c/span\u003e\u003cspan class=\"p\"\u003e)\u003c/span\u003e \u003cspan class=\"o\"\u003e-\u003c/span\u003e\u003cspan class=\"mi\"\u003e1\u003c/span\u003e \u003cspan class=\"p\"\u003e}\u003c/span\u003e \u003cspan class=\"o\"\u003e...\u003c/span\u003e  \u003cspan class=\"o\"\u003e*\u003c/span\u003e\u003cspan class=\"p\"\u003e;\u003c/span\u003e\n\u003c/span\u003e\u003c/span\u003e\u003cspan class=\"line\"\u003e\u003cspan class=\"cl\"\u003e\u003cspan class=\"nb\"\u003esay\u003c/span\u003e \u003cspan class=\"nv\"\u003e$sequence\u003c/span\u003e\u003cspan class=\"o\"\u003e.\u003c/span\u003e\u003cspan class=\"nb\"\u003eraku\u003c/span\u003e\u003cspan class=\"p\"\u003e;\u003c/span\u003e       \u003cspan class=\"c1\"\u003e# 9, 99, 999, 9999, 99999...\u003c/span\u003e\n\u003c/span\u003e\u003c/span\u003e\u003cspan class=\"line\"\u003e\u003cspan class=\"cl\"\u003e\u003cspan class=\"nb\"\u003esay\u003c/span\u003e \u003cspan class=\"o\"\u003e[+]\u003c/span\u003e \u003cspan class=\"n\"\u003esequence\u003c/span\u003e\u003cspan class=\"o\"\u003e[\u003c/span\u003e\u003cspan class=\"mi\"\u003e0\u003c/span\u003e\u003cspan class=\"o\"\u003e..^\u003c/span\u003e\u003cspan class=\"mi\"\u003e10\u003c/span\u003e\u003cspan class=\"o\"\u003e]\u003c/span\u003e\u003cspan class=\"p\"\u003e;\u003c/span\u003e \u003cspan class=\"c1\"\u003e# 11111111100\u003c/span\u003e\n\u003c/span\u003e\u003c/span\u003e\u003c/code\u003e\u003c/pre\u003e\u003c/div\u003e\u003ch2 id=\"通项为-10ⁿ---19\"\u003e通项为 (10ⁿ - 1)/9\u003c/h2\u003e\n\u003cdiv class=\"highlight\"\u003e\u003cpre tabindex=\"0\" class=\"chroma\"\u003e\u003ccode class=\"language-perl6\" data-lang=\"perl6\"\u003e\u003cspan class=\"line\"\u003e\u003cspan class=\"cl\"\u003e\u003cspan class=\"k\"\u003emy\u003c/span\u003e \u003cspan class=\"nv\"\u003e\\sequence\u003c/span\u003e \u003cspan class=\"o\"\u003e:=\u003c/span\u003e \u003cspan class=\"p\"\u003e{\u003c/span\u003e\u003cspan class=\"k\"\u003estate\u003c/span\u003e \u003cspan class=\"nv\"\u003e$n\u003c/span\u003e \u003cspan class=\"o\"\u003e=\u003c/span\u003e \u003cspan class=\"mi\"\u003e1\u003c/span\u003e\u003cspan class=\"p\"\u003e;\u003c/span\u003e \u003cspan class=\"p\"\u003e(\u003c/span\u003e\u003cspan class=\"mi\"\u003e10\u003c/span\u003e \u003cspan class=\"o\"\u003e**\u003c/span\u003e \u003cspan class=\"nv\"\u003e$n\u003c/span\u003e\u003cspan class=\"o\"\u003e++\u003c/span\u003e \u003cspan class=\"o\"\u003e-\u003c/span\u003e \u003cspan class=\"mi\"\u003e1\u003c/span\u003e\u003cspan class=\"p\"\u003e)\u003c/span\u003e \u003cspan class=\"ow\"\u003ediv\u003c/span\u003e \u003cspan class=\"mi\"\u003e9\u003c/span\u003e \u003cspan class=\"p\"\u003e}\u003c/span\u003e \u003cspan class=\"o\"\u003e...\u003c/span\u003e  \u003cspan class=\"o\"\u003e*\u003c/span\u003e\u003cspan class=\"p\"\u003e;\u003c/span\u003e\n\u003c/span\u003e\u003c/span\u003e\u003cspan class=\"line\"\u003e\u003cspan class=\"cl\"\u003e\u003cspan class=\"nb\"\u003esay\u003c/span\u003e \u003cspan class=\"n\"\u003esequence\u003c/span\u003e\u003cspan class=\"o\"\u003e.\u003c/span\u003e\u003cspan class=\"nb\"\u003eraku\u003c/span\u003e\u003cspan class=\"p\"\u003e;\u003c/span\u003e        \u003cspan class=\"c1\"\u003e# 1, 11, 111, 1111, 11111...\u003c/span\u003e\n\u003c/span\u003e\u003c/span\u003e\u003cspan class=\"line\"\u003e\u003cspan class=\"cl\"\u003e\u003cspan class=\"nb\"\u003esay\u003c/span\u003e \u003cspan class=\"o\"\u003e[+]\u003c/span\u003e \u003cspan class=\"n\"\u003esequence\u003c/span\u003e\u003cspan class=\"o\"\u003e[\u003c/span\u003e\u003cspan class=\"mi\"\u003e0\u003c/span\u003e\u003cspan class=\"o\"\u003e..^\u003c/span\u003e\u003cspan class=\"mi\"\u003e10\u003c/span\u003e\u003cspan class=\"o\"\u003e]\u003c/span\u003e\u003cspan class=\"p\"\u003e;\u003c/span\u003e \u003cspan class=\"c1\"\u003e# 1234567900\u003c/span\u003e\n\u003c/span\u003e\u003c/span\u003e\u003c/code\u003e\u003c/pre\u003e\u003c/div\u003e\u003ch2 id=\"通项为-n-1\"\u003e通项为 n²\u003c/h2\u003e\n\u003cdiv class=\"highlight\"\u003e\u003cpre tabindex=\"0\" class=\"chroma\"\u003e\u003ccode class=\"language-perl6\" data-lang=\"perl6\"\u003e\u003cspan class=\"line\"\u003e\u003cspan class=\"cl\"\u003e\u003cspan class=\"k\"\u003emy\u003c/span\u003e \u003cspan class=\"nv\"\u003e$seq\u003c/span\u003e \u003cspan class=\"o\"\u003e:=\u003c/span\u003e \u003cspan class=\"mi\"\u003e1\u003c/span\u003e\u003cspan class=\"o\"\u003e,\u003c/span\u003e\u003cspan class=\"mi\"\u003e2\u003c/span\u003e\u003cspan class=\"o\"\u003e,\u003c/span\u003e\u003cspan class=\"mi\"\u003e3\u003c/span\u003e \u003cspan class=\"o\"\u003e...\u003c/span\u003e \u003cspan class=\"o\"\u003e*\u003c/span\u003e\u003cspan class=\"p\"\u003e;\u003c/span\u003e\n\u003c/span\u003e\u003c/span\u003e\u003cspan class=\"line\"\u003e\u003cspan class=\"cl\"\u003e\u003cspan class=\"k\"\u003emy\u003c/span\u003e \u003cspan class=\"nv\"\u003e$sequence\u003c/span\u003e \u003cspan class=\"o\"\u003e:=\u003c/span\u003e \u003cspan class=\"nv\"\u003e$seq\u003c/span\u003e \u003cspan class=\"ow\"\u003eZ\u003c/span\u003e\u003cspan class=\"o\"\u003e*\u003c/span\u003e \u003cspan class=\"nv\"\u003e$seq\u003c/span\u003e\u003cspan class=\"p\"\u003e;\u003c/span\u003e\n\u003c/span\u003e\u003c/span\u003e\u003cspan class=\"line\"\u003e\u003cspan class=\"cl\"\u003e\u003cspan class=\"nb\"\u003esay\u003c/span\u003e \u003cspan class=\"nv\"\u003e$sequence\u003c/span\u003e\u003cspan class=\"o\"\u003e.\u003c/span\u003e\u003cspan class=\"nb\"\u003eraku\u003c/span\u003e\u003cspan class=\"p\"\u003e;\u003c/span\u003e       \u003cspan class=\"c1\"\u003e# 1, 4, 9, 16, 25...\u003c/span\u003e\n\u003c/span\u003e\u003c/span\u003e\u003cspan class=\"line\"\u003e\u003cspan class=\"cl\"\u003e\u003cspan class=\"nb\"\u003esay\u003c/span\u003e \u003cspan class=\"o\"\u003e[+]\u003c/span\u003e \u003cspan class=\"n\"\u003esequence\u003c/span\u003e\u003cspan class=\"o\"\u003e[\u003c/span\u003e\u003cspan class=\"mi\"\u003e0\u003c/span\u003e\u003cspan class=\"o\"\u003e..^\u003c/span\u003e\u003cspan class=\"mi\"\u003e10\u003c/span\u003e\u003cspan class=\"o\"\u003e]\u003c/span\u003e\u003cspan class=\"p\"\u003e;\u003c/span\u003e \u003cspan class=\"c1\"\u003e# 385\u003c/span\u003e\n\u003c/span\u003e\u003c/span\u003e\u003c/code\u003e\u003c/pre\u003e\u003c/div\u003e\u003cp\u003e或\u003c/p\u003e\n\u003cdiv class=\"highlight\"\u003e\u003cpre tabindex=\"0\" class=\"chroma\"\u003e\u003ccode class=\"language-perl6\" data-lang=\"perl6\"\u003e\u003cspan class=\"line\"\u003e\u003cspan class=\"cl\"\u003e\u003cspan class=\"k\"\u003emy\u003c/span\u003e \u003cspan class=\"nv\"\u003e\\sequence\u003c/span\u003e \u003cspan class=\"o\"\u003e:=\u003c/span\u003e \u003cspan class=\"p\"\u003e{\u003c/span\u003e \u003cspan class=\"k\"\u003estate\u003c/span\u003e \u003cspan class=\"nv\"\u003e$n\u003c/span\u003e \u003cspan class=\"o\"\u003e=\u003c/span\u003e \u003cspan class=\"mi\"\u003e1\u003c/span\u003e\u003cspan class=\"p\"\u003e;\u003c/span\u003e \u003cspan class=\"nv\"\u003e$n\u003c/span\u003e\u003cspan class=\"o\"\u003e++\u003c/span\u003e \u003cspan class=\"o\"\u003e**\u003c/span\u003e \u003cspan class=\"mi\"\u003e2\u003c/span\u003e \u003cspan class=\"p\"\u003e}\u003c/span\u003e \u003cspan class=\"o\"\u003e...\u003c/span\u003e \u003cspan class=\"o\"\u003e*\u003c/span\u003e\u003cspan class=\"p\"\u003e;\u003c/span\u003e\n\u003c/span\u003e\u003c/span\u003e\u003cspan class=\"line\"\u003e\u003cspan class=\"cl\"\u003e\u003cspan class=\"nb\"\u003esay\u003c/span\u003e \u003cspan class=\"n\"\u003esequence\u003c/span\u003e\u003cspan class=\"o\"\u003e.\u003c/span\u003e\u003cspan class=\"nb\"\u003eraku\u003c/span\u003e\u003cspan class=\"p\"\u003e;\u003c/span\u003e        \u003cspan class=\"c1\"\u003e# 1, 4, 9, 16, 25...\u003c/span\u003e\n\u003c/span\u003e\u003c/span\u003e\u003cspan class=\"line\"\u003e\u003cspan class=\"cl\"\u003e\u003cspan class=\"nb\"\u003esay\u003c/span\u003e \u003cspan class=\"o\"\u003e[+]\u003c/span\u003e \u003cspan class=\"n\"\u003esequence\u003c/span\u003e\u003cspan class=\"o\"\u003e[\u003c/span\u003e\u003cspan class=\"mi\"\u003e0\u003c/span\u003e\u003cspan class=\"o\"\u003e..^\u003c/span\u003e\u003cspan class=\"mi\"\u003e10\u003c/span\u003e\u003cspan class=\"o\"\u003e]\u003c/span\u003e\u003cspan class=\"p\"\u003e;\u003c/span\u003e \u003cspan class=\"c1\"\u003e# 385\u003c/span\u003e\n\u003c/span\u003e\u003c/span\u003e\u003c/code\u003e\u003c/pre\u003e\u003c/div\u003e\u003ch1 id=\"其它\"\u003e其它\u003c/h1\u003e\n\u003ch2 id=\"通项为-cosn-1π2\"\u003e通项为 cos(n-1)π/2\u003c/h2\u003e\n\u003cdiv class=\"highlight\"\u003e\u003cpre tabindex=\"0\" class=\"chroma\"\u003e\u003ccode class=\"language-perl6\" data-lang=\"perl6\"\u003e\u003cspan class=\"line\"\u003e\u003cspan class=\"cl\"\u003e\u003cspan class=\"k\"\u003emy\u003c/span\u003e \u003cspan class=\"nv\"\u003e\\sequence\u003c/span\u003e \u003cspan class=\"o\"\u003e:=\u003c/span\u003e \u003cspan class=\"p\"\u003e{\u003c/span\u003e \u003cspan class=\"k\"\u003estate\u003c/span\u003e \u003cspan class=\"nv\"\u003e$n\u003c/span\u003e \u003cspan class=\"o\"\u003e=\u003c/span\u003e \u003cspan class=\"mi\"\u003e0\u003c/span\u003e\u003cspan class=\"p\"\u003e;\u003c/span\u003e \u003cspan class=\"nv\"\u003e$n\u003c/span\u003e \u003cspan class=\"o\"\u003e+=\u003c/span\u003e \u003cspan class=\"mi\"\u003e1\u003c/span\u003e\u003cspan class=\"p\"\u003e;\u003c/span\u003e \u003cspan class=\"p\"\u003e(\u003c/span\u003e\u003cspan class=\"nb\"\u003ecos\u003c/span\u003e \u003cspan class=\"p\"\u003e(\u003c/span\u003e\u003cspan class=\"nv\"\u003e$n\u003c/span\u003e \u003cspan class=\"o\"\u003e-\u003c/span\u003e \u003cspan class=\"mi\"\u003e1\u003c/span\u003e\u003cspan class=\"p\"\u003e)\u003c/span\u003e\u003cspan class=\"o\"\u003e*\u003c/span\u003e\u003cspan class=\"no\"\u003epi\u003c/span\u003e\u003cspan class=\"o\"\u003e/\u003c/span\u003e\u003cspan class=\"mi\"\u003e2\u003c/span\u003e\u003cspan class=\"p\"\u003e)\u003c/span\u003e\u003cspan class=\"o\"\u003e.\u003c/span\u003e\u003cspan class=\"kt\"\u003eInt\u003c/span\u003e \u003cspan class=\"p\"\u003e}\u003c/span\u003e \u003cspan class=\"o\"\u003e...\u003c/span\u003e \u003cspan class=\"o\"\u003e*\u003c/span\u003e\u003cspan class=\"p\"\u003e;\u003c/span\u003e\n\u003c/span\u003e\u003c/span\u003e\u003cspan class=\"line\"\u003e\u003cspan class=\"cl\"\u003e\u003cspan class=\"nb\"\u003esay\u003c/span\u003e \u003cspan class=\"n\"\u003esequence\u003c/span\u003e\u003cspan class=\"o\"\u003e.\u003c/span\u003e\u003cspan class=\"nb\"\u003eraku\u003c/span\u003e\u003cspan class=\"p\"\u003e;\u003c/span\u003e        \u003cspan class=\"c1\"\u003e# 1, 0, -1, 0, 1, 0, -1, 0...\u003c/span\u003e\n\u003c/span\u003e\u003c/span\u003e\u003cspan class=\"line\"\u003e\u003cspan class=\"cl\"\u003e\u003cspan class=\"nb\"\u003esay\u003c/span\u003e \u003cspan class=\"o\"\u003e[+]\u003c/span\u003e \u003cspan class=\"n\"\u003esequence\u003c/span\u003e\u003cspan class=\"o\"\u003e[\u003c/span\u003e\u003cspan class=\"mi\"\u003e0\u003c/span\u003e\u003cspan class=\"o\"\u003e..^\u003c/span\u003e\u003cspan class=\"mi\"\u003e10\u003c/span\u003e\u003cspan class=\"o\"\u003e]\u003c/span\u003e\u003cspan class=\"p\"\u003e;\u003c/span\u003e \u003cspan class=\"c1\"\u003e# 1\u003c/span\u003e\n\u003c/span\u003e\u003c/span\u003e\u003c/code\u003e\u003c/pre\u003e\u003c/div\u003e\u003ch2 id=\"通项为-nn1\"\u003e通项为 n(n+1)\u003c/h2\u003e\n\u003cdiv class=\"highlight\"\u003e\u003cpre tabindex=\"0\" class=\"chroma\"\u003e\u003ccode class=\"language-perl6\" data-lang=\"perl6\"\u003e\u003cspan class=\"line\"\u003e\u003cspan class=\"cl\"\u003e\u003cspan class=\"k\"\u003emy\u003c/span\u003e \u003cspan class=\"nv\"\u003e\\sequence\u003c/span\u003e \u003cspan class=\"o\"\u003e:=\u003c/span\u003e \u003cspan class=\"p\"\u003e{\u003c/span\u003e \u003cspan class=\"k\"\u003estate\u003c/span\u003e \u003cspan class=\"nv\"\u003e$n\u003c/span\u003e \u003cspan class=\"o\"\u003e=\u003c/span\u003e \u003cspan class=\"mi\"\u003e0\u003c/span\u003e\u003cspan class=\"p\"\u003e;\u003c/span\u003e \u003cspan class=\"nv\"\u003e$n\u003c/span\u003e \u003cspan class=\"o\"\u003e+=\u003c/span\u003e \u003cspan class=\"mi\"\u003e1\u003c/span\u003e\u003cspan class=\"p\"\u003e;\u003c/span\u003e \u003cspan class=\"nv\"\u003e$n\u003c/span\u003e \u003cspan class=\"o\"\u003e*\u003c/span\u003e \u003cspan class=\"p\"\u003e(\u003c/span\u003e\u003cspan class=\"nv\"\u003e$n\u003c/span\u003e\u003cspan class=\"o\"\u003e+\u003c/span\u003e \u003cspan class=\"mi\"\u003e1\u003c/span\u003e\u003cspan class=\"p\"\u003e)\u003c/span\u003e \u003cspan class=\"p\"\u003e}\u003c/span\u003e \u003cspan class=\"o\"\u003e...\u003c/span\u003e \u003cspan class=\"o\"\u003e*\u003c/span\u003e\u003cspan class=\"p\"\u003e;\u003c/span\u003e\n\u003c/span\u003e\u003c/span\u003e\u003cspan class=\"line\"\u003e\u003cspan class=\"cl\"\u003e\u003cspan class=\"nb\"\u003esay\u003c/span\u003e \u003cspan class=\"n\"\u003esequence\u003c/span\u003e\u003cspan class=\"o\"\u003e.\u003c/span\u003e\u003cspan class=\"nb\"\u003eraku\u003c/span\u003e\u003cspan class=\"p\"\u003e;\u003c/span\u003e        \u003cspan class=\"c1\"\u003e# 2, 6, 12, 20, 30\u003c/span\u003e\n\u003c/span\u003e\u003c/span\u003e\u003cspan class=\"line\"\u003e\u003cspan class=\"cl\"\u003e\u003cspan class=\"nb\"\u003esay\u003c/span\u003e \u003cspan class=\"o\"\u003e[+]\u003c/span\u003e \u003cspan class=\"n\"\u003esequence\u003c/span\u003e\u003cspan class=\"o\"\u003e[\u003c/span\u003e\u003cspan class=\"mi\"\u003e0\u003c/span\u003e\u003cspan class=\"o\"\u003e..^\u003c/span\u003e\u003cspan class=\"mi\"\u003e10\u003c/span\u003e\u003cspan class=\"o\"\u003e]\u003c/span\u003e\u003cspan class=\"p\"\u003e;\u003c/span\u003e \u003cspan class=\"c1\"\u003e# 440\u003c/span\u003e\n\u003c/span\u003e\u003c/span\u003e\u003c/code\u003e\u003c/pre\u003e\u003c/div\u003e\u003ch2 id=\"通项为-1n\"\u003e通项为 1/n\u003c/h2\u003e\n\u003cdiv class=\"highlight\"\u003e\u003cpre tabindex=\"0\" class=\"chroma\"\u003e\u003ccode class=\"language-perl6\" data-lang=\"perl6\"\u003e\u003cspan class=\"line\"\u003e\u003cspan class=\"cl\"\u003e\u003cspan class=\"k\"\u003emy\u003c/span\u003e \u003cspan class=\"nv\"\u003e\\sequence\u003c/span\u003e \u003cspan class=\"o\"\u003e:=\u003c/span\u003e \u003cspan class=\"p\"\u003e{\u003c/span\u003e\u003cspan class=\"k\"\u003estate\u003c/span\u003e \u003cspan class=\"nv\"\u003e$n\u003c/span\u003e \u003cspan class=\"o\"\u003e=\u003c/span\u003e \u003cspan class=\"mi\"\u003e0\u003c/span\u003e\u003cspan class=\"p\"\u003e;\u003c/span\u003e \u003cspan class=\"nv\"\u003e$n\u003c/span\u003e\u003cspan class=\"o\"\u003e++\u003c/span\u003e\u003cspan class=\"p\"\u003e;\u003c/span\u003e \u003cspan class=\"kt\"\u003eRat\u003c/span\u003e\u003cspan class=\"o\"\u003e.\u003c/span\u003e\u003cspan class=\"nb\"\u003enew\u003c/span\u003e\u003cspan class=\"p\"\u003e(\u003c/span\u003e\u003cspan class=\"mi\"\u003e1\u003c/span\u003e\u003cspan class=\"o\"\u003e,\u003c/span\u003e \u003cspan class=\"nv\"\u003e$n\u003c/span\u003e\u003cspan class=\"p\"\u003e)\u003c/span\u003e \u003cspan class=\"p\"\u003e}\u003c/span\u003e \u003cspan class=\"o\"\u003e...\u003c/span\u003e \u003cspan class=\"o\"\u003e*\u003c/span\u003e\u003cspan class=\"p\"\u003e;\u003c/span\u003e\n\u003c/span\u003e\u003c/span\u003e\u003cspan class=\"line\"\u003e\u003cspan class=\"cl\"\u003e\u003cspan class=\"nb\"\u003esay\u003c/span\u003e \\\u003cspan class=\"n\"\u003esequence\u003c/span\u003e\u003cspan class=\"o\"\u003e.\u003c/span\u003e\u003cspan class=\"nb\"\u003eraku\u003c/span\u003e\u003cspan class=\"p\"\u003e;\u003c/span\u003e       \u003cspan class=\"c1\"\u003e# 1.0, 0.5, \u0026lt;1/3\u0026gt;, 0.25, 0.2, \u0026lt;1/6\u0026gt;, \u0026lt;1/7\u0026gt;...\u003c/span\u003e\n\u003c/span\u003e\u003c/span\u003e\u003cspan class=\"line\"\u003e\u003cspan class=\"cl\"\u003e\u003cspan class=\"nb\"\u003esay\u003c/span\u003e \u003cspan class=\"o\"\u003e[+]\u003c/span\u003e \u003cspan class=\"n\"\u003esequence\u003c/span\u003e\u003cspan class=\"o\"\u003e[\u003c/span\u003e\u003cspan class=\"mi\"\u003e0\u003c/span\u003e\u003cspan class=\"o\"\u003e..^\u003c/span\u003e\u003cspan class=\"mi\"\u003e10\u003c/span\u003e\u003cspan class=\"o\"\u003e]\u003c/span\u003e\u003cspan class=\"p\"\u003e;\u003c/span\u003e \u003cspan class=\"c1\"\u003e# 2.928968\u003c/span\u003e\n\u003c/span\u003e\u003c/span\u003e\u003c/code\u003e\u003c/pre\u003e\u003c/div\u003e\u003ch2 id=\"通项为-n-2\"\u003e通项为 n!\u003c/h2\u003e\n\u003cdiv class=\"highlight\"\u003e\u003cpre tabindex=\"0\" class=\"chroma\"\u003e\u003ccode class=\"language-perl6\" data-lang=\"perl6\"\u003e\u003cspan class=\"line\"\u003e\u003cspan class=\"cl\"\u003e\u003cspan class=\"k\"\u003esub\u003c/span\u003e \u003cspan class=\"nb\"\u003epostfix\u003c/span\u003e\u003cspan class=\"o\"\u003e:\u003c/span\u003e\u003cspan class=\"p\"\u003e\u0026lt;\u003c/span\u003e\u003cspan class=\"s\"\u003e!\u003c/span\u003e\u003cspan class=\"p\"\u003e\u0026gt;(\u003c/span\u003e\u003cspan class=\"nv\"\u003e$n\u003c/span\u003e \u003cspan class=\"k\"\u003ewhere\u003c/span\u003e \u003cspan class=\"nv\"\u003e$n\u003c/span\u003e \u003cspan class=\"o\"\u003e\u0026gt;\u003c/span\u003e \u003cspan class=\"mi\"\u003e0\u003c/span\u003e\u003cspan class=\"p\"\u003e)\u003c/span\u003e \u003cspan class=\"p\"\u003e{\u003c/span\u003e\n\u003c/span\u003e\u003c/span\u003e\u003cspan class=\"line\"\u003e\u003cspan class=\"cl\"\u003e    \u003cspan class=\"o\"\u003e[*]\u003c/span\u003e \u003cspan class=\"mi\"\u003e1\u003c/span\u003e\u003cspan class=\"o\"\u003e..\u003c/span\u003e\u003cspan class=\"nv\"\u003e$n\u003c/span\u003e\n\u003c/span\u003e\u003c/span\u003e\u003cspan class=\"line\"\u003e\u003cspan class=\"cl\"\u003e\u003cspan class=\"p\"\u003e}\u003c/span\u003e\n\u003c/span\u003e\u003c/span\u003e\u003cspan class=\"line\"\u003e\u003cspan class=\"cl\"\u003e\n\u003c/span\u003e\u003c/span\u003e\u003cspan class=\"line\"\u003e\u003cspan class=\"cl\"\u003e\u003cspan class=\"k\"\u003emy\u003c/span\u003e \u003cspan class=\"nv\"\u003e\\sequence\u003c/span\u003e \u003cspan class=\"o\"\u003e:=\u003c/span\u003e \u003cspan class=\"p\"\u003e{\u003c/span\u003e \u003cspan class=\"k\"\u003estate\u003c/span\u003e \u003cspan class=\"nv\"\u003e$n\u003c/span\u003e \u003cspan class=\"o\"\u003e=\u003c/span\u003e \u003cspan class=\"mi\"\u003e0\u003c/span\u003e\u003cspan class=\"p\"\u003e;\u003c/span\u003e \u003cspan class=\"nv\"\u003e$n\u003c/span\u003e\u003cspan class=\"o\"\u003e++\u003c/span\u003e\u003cspan class=\"p\"\u003e;\u003c/span\u003e \u003cspan class=\"nv\"\u003e$n\u003c/span\u003e\u003cspan class=\"o\"\u003e!\u003c/span\u003e \u003cspan class=\"p\"\u003e}\u003c/span\u003e \u003cspan class=\"o\"\u003e...\u003c/span\u003e \u003cspan class=\"o\"\u003e*\u003c/span\u003e\u003cspan class=\"p\"\u003e;\u003c/span\u003e\n\u003c/span\u003e\u003c/span\u003e\u003cspan class=\"line\"\u003e\u003cspan class=\"cl\"\u003e\u003cspan class=\"nb\"\u003esay\u003c/span\u003e \u003cspan class=\"n\"\u003esequence\u003c/span\u003e\u003cspan class=\"o\"\u003e.\u003c/span\u003e\u003cspan class=\"nb\"\u003eraku\u003c/span\u003e\u003cspan class=\"p\"\u003e;\u003c/span\u003e        \u003cspan class=\"c1\"\u003e# 1, 2, 6, 24, 120...\u003c/span\u003e\n\u003c/span\u003e\u003c/span\u003e\u003cspan class=\"line\"\u003e\u003cspan class=\"cl\"\u003e\u003cspan class=\"nb\"\u003esay\u003c/span\u003e \u003cspan class=\"o\"\u003e[+]\u003c/span\u003e \u003cspan class=\"n\"\u003esequence\u003c/span\u003e\u003cspan class=\"o\"\u003e[\u003c/span\u003e\u003cspan class=\"mi\"\u003e0\u003c/span\u003e\u003cspan class=\"o\"\u003e..^\u003c/span\u003e\u003cspan class=\"mi\"\u003e10\u003c/span\u003e\u003cspan class=\"o\"\u003e]\u003c/span\u003e\u003cspan class=\"p\"\u003e;\u003c/span\u003e \u003cspan class=\"c1\"\u003e# 4037913\u003c/span\u003e\n\u003c/span\u003e\u003c/span\u003e\u003c/code\u003e\u003c/pre\u003e\u003c/div\u003e","text":"斐波那契数列(Fibonacci sequence) lazy my \\sequence = 1, 1, {$^a + $^b } ... *; say sequence.raku; # 1, 1, 2, 3, 5... say [+] sequence[0..^10]; # 143 等差数列(arithmetic sequence) 通项为 n lazy my \\sequence = 1, 2, 3 ... *; say sequence.raku; # 1, 2, 3, 4, 5... say [+] sequence[0..^10]; # 55 通项为 2n lazy my \\sequence = 2, 4, 6 ... *; say sequence.raku; # 2, 4, 6, 8, 10 say [+] sequence[0..^10]; # 110 通项为 2n - 1 lazy my \\sequence = 1, 3, 5 ... *; say sequence.raku; # 1, 3, 5, 7, 9... say [+] sequence[0..^10]; # 100 等比数列 通项为 2ⁿ⁻¹ my \\sequence := 1, 2, 4 ... *; say sequence.raku; # 1, 2, 4, 8, 16... say [+] sequence[0..^10]; # 1023 或:\nmy \\sequence := { state $n = 1; 2 ** ($n++ -1) } ... *; say sequence.raku; # 1, 2, 4, 8, 16... say [+] sequence[0..^10]; # 1023 通项为 -1ⁿ lazy my \\sequence = -1,1,-1 ... *; say sequence.raku; # -1, 1, -1, 1, -1... say [+] sequence[0..^10]; # 0 通项为 -1ⁿ⁺¹ lazy my \\sequence = 1,-1,1 ... *; say sequence.raku; # 1, -1, 1, -1, 1... say [+] sequence[0..^10]; # 0 指数数列 通项为 10ⁿ - 1 my \\sequence := 9, 99, -\u0026gt; $a { ($a ~ \u0026#39;9\u0026#39;).Int } ... *; say $sequence.raku; # 9, 99, 999, 9999, 99999... say [+] sequence[0..^10]; # 11111111100 或:\nmy \\sequence := {state $n = 1; (10 ** $n++) -1 } ... *; say $sequence.raku; # 9, 99, 999, 9999, 99999... say [+] sequence[0..^10]; # 11111111100 通项为 (10ⁿ - 1)/9 my \\sequence := {state $n = 1; (10 ** $n++ - 1) div 9 } ... *; say sequence.raku; # 1, 11, 111, 1111, 11111... say [+] sequence[0..^10]; # 1234567900 通项为 n² my $seq := 1,2,3 ... *; my $sequence := $seq Z* $seq; say $sequence.raku; # 1, 4, 9, 16, 25... say [+] sequence[0..^10]; # 385 或\nmy \\sequence := { state $n = 1; $n++ ** 2 } ... *; say sequence.raku; # 1, 4, 9, 16, 25... say [+] sequence[0..^10]; # 385 其它 通项为 cos(n-1)π/2 my \\sequence := { state $n = 0; $n += 1; (cos ($n - 1)*pi/2).Int } ... *; say sequence.raku; # 1, 0, -1, 0, 1, 0, -1, 0... say [+] sequence[0..^10]; # 1 通项为 n(n+1) my \\sequence := { state $n = 0; $n += 1; $n * ($n+ 1) } ... *; say sequence.raku; # 2, 6, 12, 20, 30 say [+] sequence[0..^10]; # 440 通项为 1/n my \\sequence := {state $n = 0; $n++; Rat.new(1, $n) } ... *; say \\sequence.raku; # 1.0, 0.5, \u0026lt;1/3\u0026gt;, 0.25, 0.2, \u0026lt;1/6\u0026gt;, \u0026lt;1/7\u0026gt;... say [+] sequence[0..^10]; # 2.928968 通项为 n! sub postfix:\u0026lt;!\u0026gt;($n where $n \u0026gt; 0) { [*] 1..$n } my \\sequence := { state $n = 0; $n++; $n! } ... *; say sequence.raku; # 1, 2, 6, 24, 120... say [+] sequence[0..^10]; # 4037913 "},"name":"数列","published":"2020-06-30T13:33:26+08:00","summary":"斐波那契数列(Fibonacci sequence) lazy my \\sequence = 1, 1, {$^a + $^b } ... *; say sequence.raku; # 1, 1, 2, 3, 5... say [+] sequence[0..^10]; # 143 等差数列(arithmetic sequence) 通项为 n lazy my \\sequence = 1, 2, 3 ... *; say sequence.raku; # 1, 2, 3, 4, 5... say [+] sequence[0..^10]; # 55 通项为 2n lazy my \\sequence = 2, 4, 6 ... *; say sequence.raku; # 2, 4, 6, 8, 10 say [+] sequence[0.","type":"entry","url":"https://ohmycloud.github.io/posts/2020-06-30-sequence/"}